intelhex/__init__.py
intelhex/__main__.py
intelhex/__version__.py
intelhex/bench.py
intelhex/compat.py
intelhex/getsizeof.py
intelhex/test.py
intelhex-2.2.1.data/scripts/bin2hex.py
intelhex-2.2.1.data/scripts/hex2bin.py
intelhex-2.2.1.data/scripts/hex2dump.py
intelhex-2.2.1.data/scripts/hexdiff.py
intelhex-2.2.1.data/scripts/hexinfo.py
intelhex-2.2.1.data/scripts/hexmerge.py
intelhex-2.2.1.dist-info/DESCRIPTION.rst
intelhex-2.2.1.dist-info/METADATA
intelhex-2.2.1.dist-info/RECORD
intelhex-2.2.1.dist-info/WHEEL
intelhex-2.2.1.dist-info/metadata.json
intelhex-2.2.1.dist-info/top_level.txt
