Metadata-Version: 1.1
Name: intelhex
Version: 2.2.1
Summary: Python library for Intel HEX files manipulations
Home-page: https://pypi.python.org/pypi/IntelHex
Author: Alexander Belchenko
Author-email: alexander.belchenko@gmail.com
License: BSD
Keywords: Intel HEX hex2bin HEX8
Platform: UNKNOWN
Classifier: Development Status :: 5 - Production/Stable
Classifier: Environment :: Console
Classifier: Intended Audience :: Developers
Classifier: License :: OSI Approved :: BSD License
Classifier: Operating System :: OS Independent
Classifier: Programming Language :: Python
